LICENSE
zen_knit/__init__.py
zen_knit/cli.py
zen_knit/data_types/__init__.py
zen_knit/executor/__init__.py
zen_knit/formattor/__init__.py
zen_knit/formattor/base_formatter.py
zen_knit/formattor/html_formatter.py
zen_knit/formattor/html_support/__init__.py
zen_knit/formattor/html_support/bootstrap.py
zen_knit/formattor/html_support/cerulean.py
zen_knit/formattor/html_support/journal.py
zen_knit/formattor/html_support/skleton.py
zen_knit/formattor/makrdown_math.py
zen_knit/formattor/markdown_formtter.py
zen_knit/formattor/tex_formatter.py
zen_knit/organizer/__init__.py
zen_knit/parser/__init__.py
zen_knit/publish/__init__.py
zen_knit/publish/core/__init__.py
zen_knit/publish/core/publish.py
zen_knit/publish/core/worker.py
zen_knit/publish/support/__init__.py
zen_knit/publish/support/cred.py
zen_knit/publish_cli.py
zen_knit/reader/__init__.py
zen_knit-0.2.5.dist-info/entry_points.txt
zen_knit-0.2.5.dist-info/LICENSE
zen_knit-0.2.5.dist-info/WHEEL
zen_knit-0.2.5.dist-info/METADATA
zen_knit-0.2.5.dist-info/RECORD
