Metadata-Version: 2.1
Name: zen-knit
Version: 0.2.5
Summary: Zen-Knit is a formal (PDF), informal (HTML) report generator for data analyst and data scientist who wants to use python. Rmarkdown Alternative for Python, It also allow you to publish reports to Zen Reportz Enterprise or community edition
Home-page: https://github.com/Zen-Reportz/zen_knit
License: MIT
Author: Zen
Author-email: zenreportz@protonmail.com
Requires-Python: >=3.7,<4.0
Classifier: License :: OSI Approved :: MIT License
Classifier: Programming Language :: Python :: 3
Classifier: Programming Language :: Python :: 3.10
Classifier: Programming Language :: Python :: 3.7
Classifier: Programming Language :: Python :: 3.8
Classifier: Programming Language :: Python :: 3.9
Requires-Dist: Markdown (>=3.3.6,<4.0.0)
Requires-Dist: SQLAlchemy (>=1.4.29,<2.0.0)
Requires-Dist: click (>=8.0.3,<9.0.0)
Requires-Dist: ipykernel (>=6.0.0)
Requires-Dist: ipython (>=7.0)
Requires-Dist: joblib (>=1.1.0,<2.0.0)
Requires-Dist: jupyter-client (>=7.1.0,<8.0.0)
Requires-Dist: nbconvert (>=6.0.0)
Requires-Dist: nbformat (>=5.1.3,<6.0.0)
Requires-Dist: oyaml (>=1.0,<2.0)
Requires-Dist: pydantic (>=1.8.2,<2.0.0)
Requires-Dist: requests (>=2.27.1,<3.0.0)
Project-URL: Repository, https://github.com/Zen-Reportz/zen_knit
